LICENSE
MANIFEST.in
README.rst
setup.py
django_polls_sunwei.egg-info/PKG-INFO
django_polls_sunwei.egg-info/SOURCES.txt
django_polls_sunwei.egg-info/dependency_links.txt
django_polls_sunwei.egg-info/top_level.txt
polls/__init__.py
polls/admin.py
polls/apps.py
polls/models.py
polls/tests.py
polls/urls.py
polls/views.py
polls/migrations/0001_initial.py
polls/migrations/__init__.py
polls/static/polls/style.css
polls/static/polls/images/background.gif
polls/templates/polls/detail.html
polls/templates/polls/index.html
polls/templates/polls/results.html